simple_zuora_client/__init__.py
simple_zuora_client/zuora_basic_client.py
simple_zuora_client/zuora_client.py
simple_zuora_client/client_libs/__init__.py
simple_zuora_client/client_libs/data_wrappers.py
simple_zuora_client/client_libs/zuora_client_exceptions.py
simple_zuora_client-0.1.6.dist-info/LICENSE
simple_zuora_client-0.1.6.dist-info/METADATA
simple_zuora_client-0.1.6.dist-info/WHEEL
simple_zuora_client-0.1.6.dist-info/top_level.txt
simple_zuora_client-0.1.6.dist-info/RECORD
