Metadata-Version: 2.1
Name: simple-zuora-client
Version: 0.1.6
Summary: Simple Zuora Client
Home-page: https://gitlab.com/sergwy/simple-zuora-client
Maintainer: Sergey Yakimov
Maintainer-email: sergwy@gmail.com
License: Simple Zuora(R) Client
Requires-Dist: setuptools (~=49.3.2)
Requires-Dist: oauthlib (~=3.1.0)
Requires-Dist: requests (~=2.24.0)
Requires-Dist: requests-oauthlib
Requires-Dist: simplejson (~=3.17.2)
